cctx/__init__.py
cctx-1.0.0.dist-info/DESCRIPTION.rst
cctx-1.0.0.dist-info/METADATA
cctx-1.0.0.dist-info/RECORD
cctx-1.0.0.dist-info/WHEEL
cctx-1.0.0.dist-info/metadata.json
cctx-1.0.0.dist-info/top_level.txt
