Metadata-Version: 1.1
Name: cctx
Version: 1.0.0
Summary: A JavaScript / Python / PHP cryptocurrency trading library with support for 90+ exchanges
Home-page: https://ccxt.trade
Author: Igor Kroitor
Author-email: igor.kroitor@gmail.com
License: MIT
Keywords: algorithmic,algotrading,altcoin,altcoins,api,arbitrage,backtest,backtesting,bitcoin,bot,btc,ccxt,cny,coin,coins,crypto,cryptocurrency,crypto currency,crypto market,currency,currencies,darkcoin,dash,digital currency,doge,dogecoin,e-commerce,etc,eth,ether,ethereum,exchange,exchanges,eur,framework,invest,investing,investor,library,light,litecoin,ltc,market,market data,markets,merchandise,merchant,minimal,order,orderbook,order book,price,price data,pricefeed,private,public,ripple,strategy,
Platform: UNKNOWN
Classifier: Development Status :: 4 - Beta
Classifier: Intended Audience :: Developers
Classifier: Intended Audience :: Financial and Insurance Industry
Classifier: Intended Audience :: Information Technology
Classifier: Topic :: Software Development :: Build Tools
Classifier: Topic :: Office/Business :: Financial :: Investment
Classifier: License :: OSI Approved :: MIT License
Classifier: Programming Language :: Python :: 2
Classifier: Programming Language :: Python :: 2.7
Classifier: Programming Language :: Python :: 3
Classifier: Programming Language :: Python :: 3.3
Classifier: Programming Language :: Python :: 3.4
Classifier: Programming Language :: Python :: 3.5
Classifier: Programming Language :: Python :: 3.6
Classifier: Programming Language :: JavaScript
Classifier: Programming Language :: PHP
Classifier: Operating System :: OS Independent
Classifier: Environment :: Console
